{
  "fill" : "automatic",
  "groups" : [
    {
      "layers" : [
        {
          "glass" : true,
          "image-name" : "AppIconBadge.png",
          "name" : "AppIconBadge",
          "position" : {
            "scale" : 1,
            "translation-in-points" : [
              163.71875,
              -230.875
            ]
          }
        },
        {
          "fill" : "none",
          "glass" : true,
          "hidden" : false,
          "image-name" : "Cloud.png",
          "name" : "Cloud",
          "position" : {
            "scale" : 0.77,
            "translation-in-points" : [
              0,
              0
            ]
          }
        }
      ],
      "shadow" : {
        "kind" : "neutral",
        "opacity" : 0.5
      },
      "translucency" : {
        "enabled" : true,
        "value" : 0.5
      }
    }
  ],
  "supported-platforms" : {
    "squares" : "shared"
  }
}